LICENSE
MANIFEST.in
README.md
setup.py
libpythonpro_arturlauth/__init__.py
libpythonpro_arturlauth/github_api.py
libpythonpro_arturlauth.egg-info/PKG-INFO
libpythonpro_arturlauth.egg-info/SOURCES.txt
libpythonpro_arturlauth.egg-info/dependency_links.txt
libpythonpro_arturlauth.egg-info/not-zip-safe
libpythonpro_arturlauth.egg-info/requires.txt
libpythonpro_arturlauth.egg-info/top_level.txt